<?xml version="1.0" encoding="UTF-8"?>
<objects serializationModel="Studio.02.03.00">
	<object class="AudioFile" id="{919a711a-71e9-4e41-ac7d-a3bb071a5315}">
		<property name="assetPath">
			<value>FOOTSTEP_PLASTIC_1.wav</value>
		</property>
		<property name="frequencyInKHz">
			<value>48</value>
		</property>
		<property name="channelCount">
			<value>2</value>
		</property>
		<property name="length">
			<value>1.8736041666666667</value>
		</property>
		<relationship name="masterAssetFolder">
			<destination>{2bee4d2d-a272-4277-bab5-159242a81bc7}</destination>
		</relationship>
	</object>
</objects>
